paramnb/.version
paramnb/__init__.py
paramnb/__main__.py
paramnb/util.py
paramnb/view.py
paramnb/widgets.py
paramnb/examples/user_guide/AdditionalFeatures.ipynb
paramnb/examples/user_guide/JSONInit.ipynb
paramnb/examples/user_guide/index.ipynb
paramnb/examples/user_guide/images/intro.gif
paramnb/examples/user_guide/images/stock_dashboard.png
paramnb/tests/__init__.py
paramnb/tests/test_dummy.py
paramnb-2.0.4.dist-info/LICENSE.txt
paramnb-2.0.4.dist-info/METADATA
paramnb-2.0.4.dist-info/RECORD
paramnb-2.0.4.dist-info/WHEEL
paramnb-2.0.4.dist-info/entry_points.txt
paramnb-2.0.4.dist-info/top_level.txt
