Metadata-Version: 2.1
Name: paramnb
Version: 2.0.4
Summary: Generate ipywidgets from Parameterized objects in the notebook
Home-page: https://paramnb.pyviz.org
Author: PyViz
Author-email: holoviews@gmail.com
Maintainer: PyViz
Maintainer-email: holoviews@gmail.com
License: BSD 3-Clause License
Project-URL: Bug Tracker, https://github.com/ioam/paramnb/issues
Project-URL: Documentation, https://paramnb.pyviz.org
Project-URL: Source Code, https://github.com/ioam/paramnb
Platform: UNKNOWN
Classifier: License :: OSI Approved :: BSD License
Classifier: Operating System :: OS Independent
Classifier: Programming Language :: Python
Classifier: Programming Language :: Python :: 2.7
Classifier: Programming Language :: Python :: 3.5
Classifier: Programming Language :: Python :: 3.6
Classifier: Development Status :: 4 - Beta
Requires-Python: >=2.7
Provides-Extra: tests
Provides-Extra: examples
